{
  "config": {
    "seed": 42,
    "num_bins": 32,
    "topk_list": [
      1,
      4,
      8,
      16
    ],
    "prefix_ks": [
      0,
      1,
      2,
      4,
      8,
      16
    ],
    "diag_w": 8,
    "exclude_self": false,
    "num_samples": 64,
    "dataset_mix": {
      "hotpot": {
        "name": "hotpot_qa",
        "config": "distractor",
        "split": "train"
      },
      "xsum": {
        "name": "xsum",
        "config": null,
        "split": "train"
      }
    },
    "scales_by_layer": {
      "10": [
        1.0,
        4.0,
        16.0,
        64.0,
        256.0,
        1024.0,
        4096.0,
        16384.0
      ],
      "11": [
        1.0,
        4.0,
        16.0,
        64.0,
        256.0,
        1024.0,
        4096.0,
        16384.0
      ]
    },
    "thresholds": {
      "null_p0": 0.8,
      "active_p0": 0.2,
      "entropy_top20_threshold": 1.6766063247105236,
      "s_eff_bottom20_threshold": 3.9051827686684777,
      "s_eff_top20_threshold": 5.111225431016537,
      "entropy_candidates": 158712,
      "s_eff_candidates": 158712
    },
    "filter_rules": {
      "query_key_masked_by_attention_mask": true,
      "exclude_pad_token": true,
      "exclude_eos_token": true,
      "causal_key_le_query": true,
      "exclude_self": false
    }
  },
  "heads": {
    "L11_H8": {
      "hotpotqa": {
        "count": 16384,
        "state_counts": {
          "NULL": 0,
          "UNIFORM": 4132,
          "SMALL": 3133,
          "LARGE": 898,
          "OTHER": 8221
        },
        "state_ratio": {
          "NULL": 0.0,
          "UNIFORM": 0.252197265625,
          "SMALL": 0.19122314453125,
          "LARGE": 0.0548095703125,
          "OTHER": 0.50177001953125
        },
        "p0": {
          "mean_std": {
            "mean": 0.06364295953872556,
            "std": 0.044544930848610796
          },
          "quantiles": {
            "p50": 0.05133591126650572,
            "p90": 0.11263277716934682,
            "p99": 0.24176088220439854
          }
        },
        "entropy": {
          "mean_std": {
            "mean": 1.5783748223159515,
            "std": 0.14627657689410517
          },
          "quantiles": {
            "p50": 1.5989248104334182,
            "p90": 1.7495626992927136,
            "p99": 1.8471559081544022
          }
        },
        "s_eff": {
          "mean_std": {
            "mean": 4.433457260798143,
            "std": 0.6505210459120204
          },
          "quantiles": {
            "p50": 4.325937800326001,
            "p90": 5.287670858343788,
            "p99": 6.486782667936213
          }
        }
      },
      "xsum": {
        "count": 10486,
        "state_counts": {
          "NULL": 0,
          "UNIFORM": 3157,
          "SMALL": 2383,
          "LARGE": 725,
          "OTHER": 4221
        },
        "state_ratio": {
          "NULL": 0.0,
          "UNIFORM": 0.30106809078771696,
          "SMALL": 0.22725538813656304,
          "LARGE": 0.06913980545489223,
          "OTHER": 0.40253671562082777
        },
        "p0": {
          "mean_std": {
            "mean": 0.061207289257773,
            "std": 0.04514957051471416
          },
          "quantiles": {
            "p50": 0.04849003627896309,
            "p90": 0.11118833580985665,
            "p99": 0.2404859909787774
          }
        },
        "entropy": {
          "mean_std": {
            "mean": 1.5916431998449942,
            "std": 0.14908378726779656
          },
          "quantiles": {
            "p50": 1.614560131509553,
            "p90": 1.7625069550231576,
            "p99": 1.859903894338249
          }
        },
        "s_eff": {
          "mean_std": {
            "mean": 4.409802661930079,
            "std": 0.7131715828443884
          },
          "quantiles": {
            "p50": 4.278415864842753,
            "p90": 5.404316105880363,
            "p99": 6.634916016817542
          }
        }
      },
      "all": {
        "count": 26870,
        "state_counts": {
          "NULL": 0,
          "UNIFORM": 7289,
          "SMALL": 5516,
          "LARGE": 1623,
          "OTHER": 12442
        },
        "state_ratio": {
          "NULL": 0.0,
          "UNIFORM": 0.2712690733159658,
          "SMALL": 0.2052847041310011,
          "LARGE": 0.06040193524376628,
          "OTHER": 0.46304428730926683
        },
        "p0": {
          "mean_std": {
            "mean": 0.0626924407978968,
            "std": 0.0447976211910903
          },
          "quantiles": {
            "p50": 0.050316598266363144,
            "p90": 0.11208907859399918,
            "p99": 0.24116633391007833
          }
        },
        "entropy": {
          "mean_std": {
            "mean": 1.5835527980051793,
            "std": 0.147520505968096
          },
          "quantiles": {
            "p50": 1.60498280824143,
            "p90": 1.755130646874425,
            "p99": 1.8524928817474473
          }
        },
        "s_eff": {
          "mean_std": {
            "mean": 4.424226068995742,
            "std": 0.6757604229267491
          },
          "quantiles": {
            "p50": 4.309556990516276,
            "p90": 5.332993204760298,
            "p99": 6.548279609762515
          }
        }
      }
    },
    "L11_H10": {
      "hotpotqa": {
        "count": 16384,
        "state_counts": {
          "NULL": 0,
          "UNIFORM": 4132,
          "SMALL": 3133,
          "LARGE": 898,
          "OTHER": 8221
        },
        "state_ratio": {
          "NULL": 0.0,
          "UNIFORM": 0.252197265625,
          "SMALL": 0.19122314453125,
          "LARGE": 0.0548095703125,
          "OTHER": 0.50177001953125
        },
        "p0": {
          "mean_std": {
            "mean": 0.06364295953872556,
            "std": 0.044544930848610796
          },
          "quantiles": {
            "p50": 0.05133591126650572,
            "p90": 0.11263277716934682,
            "p99": 0.24176088220439854
          }
        },
        "entropy": {
          "mean_std": {
            "mean": 1.5783748223159515,
            "std": 0.14627657689410517
          },
          "quantiles": {
            "p50": 1.5989248104334182,
            "p90": 1.7495626992927136,
            "p99": 1.8471559081544022
          }
        },
        "s_eff": {
          "mean_std": {
            "mean": 4.433457260798143,
            "std": 0.6505210459120204
          },
          "quantiles": {
            "p50": 4.325937800326001,
            "p90": 5.287670858343788,
            "p99": 6.486782667936213
          }
        }
      },
      "xsum": {
        "count": 10486,
        "state_counts": {
          "NULL": 0,
          "UNIFORM": 3157,
          "SMALL": 2383,
          "LARGE": 725,
          "OTHER": 4221
        },
        "state_ratio": {
          "NULL": 0.0,
          "UNIFORM": 0.30106809078771696,
          "SMALL": 0.22725538813656304,
          "LARGE": 0.06913980545489223,
          "OTHER": 0.40253671562082777
        },
        "p0": {
          "mean_std": {
            "mean": 0.061207289257773,
            "std": 0.04514957051471416
          },
          "quantiles": {
            "p50": 0.04849003627896309,
            "p90": 0.11118833580985665,
            "p99": 0.2404859909787774
          }
        },
        "entropy": {
          "mean_std": {
            "mean": 1.5916431998449942,
            "std": 0.14908378726779656
          },
          "quantiles": {
            "p50": 1.614560131509553,
            "p90": 1.7625069550231576,
            "p99": 1.859903894338249
          }
        },
        "s_eff": {
          "mean_std": {
            "mean": 4.409802661930079,
            "std": 0.7131715828443884
          },
          "quantiles": {
            "p50": 4.278415864842753,
            "p90": 5.404316105880363,
            "p99": 6.634916016817542
          }
        }
      },
      "all": {
        "count": 26870,
        "state_counts": {
          "NULL": 0,
          "UNIFORM": 7289,
          "SMALL": 5516,
          "LARGE": 1623,
          "OTHER": 12442
        },
        "state_ratio": {
          "NULL": 0.0,
          "UNIFORM": 0.2712690733159658,
          "SMALL": 0.2052847041310011,
          "LARGE": 0.06040193524376628,
          "OTHER": 0.46304428730926683
        },
        "p0": {
          "mean_std": {
            "mean": 0.0626924407978968,
            "std": 0.0447976211910903
          },
          "quantiles": {
            "p50": 0.050316598266363144,
            "p90": 0.11208907859399918,
            "p99": 0.24116633391007833
          }
        },
        "entropy": {
          "mean_std": {
            "mean": 1.5835527980051793,
            "std": 0.147520505968096
          },
          "quantiles": {
            "p50": 1.60498280824143,
            "p90": 1.755130646874425,
            "p99": 1.8524928817474473
          }
        },
        "s_eff": {
          "mean_std": {
            "mean": 4.424226068995742,
            "std": 0.6757604229267491
          },
          "quantiles": {
            "p50": 4.309556990516276,
            "p90": 5.332993204760298,
            "p99": 6.548279609762515
          }
        }
      }
    },
    "L11_H0": {
      "hotpotqa": {
        "count": 16384,
        "state_counts": {
          "NULL": 0,
          "UNIFORM": 4132,
          "SMALL": 3133,
          "LARGE": 898,
          "OTHER": 8221
        },
        "state_ratio": {
          "NULL": 0.0,
          "UNIFORM": 0.252197265625,
          "SMALL": 0.19122314453125,
          "LARGE": 0.0548095703125,
          "OTHER": 0.50177001953125
        },
        "p0": {
          "mean_std": {
            "mean": 0.06364295953872556,
            "std": 0.044544930848610796
          },
          "quantiles": {
            "p50": 0.05133591126650572,
            "p90": 0.11263277716934682,
            "p99": 0.24176088220439854
          }
        },
        "entropy": {
          "mean_std": {
            "mean": 1.5783748223159515,
            "std": 0.14627657689410517
          },
          "quantiles": {
            "p50": 1.5989248104334182,
            "p90": 1.7495626992927136,
            "p99": 1.8471559081544022
          }
        },
        "s_eff": {
          "mean_std": {
            "mean": 4.433457260798143,
            "std": 0.6505210459120204
          },
          "quantiles": {
            "p50": 4.325937800326001,
            "p90": 5.287670858343788,
            "p99": 6.486782667936213
          }
        }
      },
      "xsum": {
        "count": 10486,
        "state_counts": {
          "NULL": 0,
          "UNIFORM": 3157,
          "SMALL": 2383,
          "LARGE": 725,
          "OTHER": 4221
        },
        "state_ratio": {
          "NULL": 0.0,
          "UNIFORM": 0.30106809078771696,
          "SMALL": 0.22725538813656304,
          "LARGE": 0.06913980545489223,
          "OTHER": 0.40253671562082777
        },
        "p0": {
          "mean_std": {
            "mean": 0.061207289257773,
            "std": 0.04514957051471416
          },
          "quantiles": {
            "p50": 0.04849003627896309,
            "p90": 0.11118833580985665,
            "p99": 0.2404859909787774
          }
        },
        "entropy": {
          "mean_std": {
            "mean": 1.5916431998449942,
            "std": 0.14908378726779656
          },
          "quantiles": {
            "p50": 1.614560131509553,
            "p90": 1.7625069550231576,
            "p99": 1.859903894338249
          }
        },
        "s_eff": {
          "mean_std": {
            "mean": 4.409802661930079,
            "std": 0.7131715828443884
          },
          "quantiles": {
            "p50": 4.278415864842753,
            "p90": 5.404316105880363,
            "p99": 6.634916016817542
          }
        }
      },
      "all": {
        "count": 26870,
        "state_counts": {
          "NULL": 0,
          "UNIFORM": 7289,
          "SMALL": 5516,
          "LARGE": 1623,
          "OTHER": 12442
        },
        "state_ratio": {
          "NULL": 0.0,
          "UNIFORM": 0.2712690733159658,
          "SMALL": 0.2052847041310011,
          "LARGE": 0.06040193524376628,
          "OTHER": 0.46304428730926683
        },
        "p0": {
          "mean_std": {
            "mean": 0.0626924407978968,
            "std": 0.0447976211910903
          },
          "quantiles": {
            "p50": 0.050316598266363144,
            "p90": 0.11208907859399918,
            "p99": 0.24116633391007833
          }
        },
        "entropy": {
          "mean_std": {
            "mean": 1.5835527980051793,
            "std": 0.147520505968096
          },
          "quantiles": {
            "p50": 1.60498280824143,
            "p90": 1.755130646874425,
            "p99": 1.8524928817474473
          }
        },
        "s_eff": {
          "mean_std": {
            "mean": 4.424226068995742,
            "std": 0.6757604229267491
          },
          "quantiles": {
            "p50": 4.309556990516276,
            "p90": 5.332993204760298,
            "p99": 6.548279609762515
          }
        }
      }
    },
    "L10_H11": {
      "hotpotqa": {
        "count": 16384,
        "state_counts": {
          "NULL": 0,
          "UNIFORM": 1929,
          "SMALL": 3031,
          "LARGE": 3126,
          "OTHER": 8298
        },
        "state_ratio": {
          "NULL": 0.0,
          "UNIFORM": 0.11773681640625,
          "SMALL": 0.18499755859375,
          "LARGE": 0.1907958984375,
          "OTHER": 0.5064697265625
        },
        "p0": {
          "mean_std": {
            "mean": 0.049643461284802015,
            "std": 0.030171847777887454
          },
          "quantiles": {
            "p50": 0.04178311675786972,
            "p90": 0.08457316178828479,
            "p99": 0.16792343001812704
          }
        },
        "entropy": {
          "mean_std": {
            "mean": 1.4734613366591036,
            "std": 0.17667414553603852
          },
          "quantiles": {
            "p50": 1.4960775599894791,
            "p90": 1.6900896384400954,
            "p99": 1.8049682735736834
          }
        },
        "s_eff": {
          "mean_std": {
            "mean": 4.553102337836345,
            "std": 0.6345255115888973
          },
          "quantiles": {
            "p50": 4.58083980401199,
            "p90": 5.34119405181383,
            "p99": 5.939068889108965
          }
        }
      },
      "xsum": {
        "count": 10486,
        "state_counts": {
          "NULL": 0,
          "UNIFORM": 1363,
          "SMALL": 1484,
          "LARGE": 2872,
          "OTHER": 4767
        },
        "state_ratio": {
          "NULL": 0.0,
          "UNIFORM": 0.1299828342551974,
          "SMALL": 0.14152202937249667,
          "LARGE": 0.27388899485027657,
          "OTHER": 0.4546061415220294
        },
        "p0": {
          "mean_std": {
            "mean": 0.06418167062313532,
            "std": 0.04765356682546106
          },
          "quantiles": {
            "p50": 0.0501585379242897,
            "p90": 0.11942879064008594,
            "p99": 0.25640989937819514
          }
        },
        "entropy": {
          "mean_std": {
            "mean": 1.4873130528587912,
            "std": 0.1773318471728427
          },
          "quantiles": {
            "p50": 1.5103191909700038,
            "p90": 1.7026533257737282,
            "p99": 1.8199454131573884
          }
        },
        "s_eff": {
          "mean_std": {
            "mean": 4.750551226813394,
            "std": 0.7126803417098657
          },
          "quantiles": {
            "p50": 4.79614042560852,
            "p90": 5.631939380785089,
            "p99": 6.418864512366683
          }
        }
      },
      "all": {
        "count": 26870,
        "state_counts": {
          "NULL": 0,
          "UNIFORM": 3292,
          "SMALL": 4515,
          "LARGE": 5998,
          "OTHER": 13065
        },
        "state_ratio": {
          "NULL": 0.0,
          "UNIFORM": 0.12251581689616672,
          "SMALL": 0.1680312616300707,
          "LARGE": 0.2232229251953852,
          "OTHER": 0.4862299962783774
        },
        "p0": {
          "mean_std": {
            "mean": 0.05531698801058404,
            "std": 0.038620943143403884
          },
          "quantiles": {
            "p50": 0.04444117471575737,
            "p90": 0.09778977613896132,
            "p99": 0.21069763645529765
          }
        },
        "entropy": {
          "mean_std": {
            "mean": 1.4788669598846313,
            "std": 0.1770600801375222
          },
          "quantiles": {
            "p50": 1.5007785575020858,
            "p90": 1.695103605367428,
            "p99": 1.810876462676003
          }
        },
        "s_eff": {
          "mean_std": {
            "mean": 4.630156638164344,
            "std": 0.6730446873208454
          },
          "quantiles": {
            "p50": 4.6553604499057535,
            "p90": 5.459600870173321,
            "p99": 6.174328532197354
          }
        }
      }
    },
    "L10_H5": {
      "hotpotqa": {
        "count": 16384,
        "state_counts": {
          "NULL": 0,
          "UNIFORM": 1929,
          "SMALL": 3031,
          "LARGE": 3126,
          "OTHER": 8298
        },
        "state_ratio": {
          "NULL": 0.0,
          "UNIFORM": 0.11773681640625,
          "SMALL": 0.18499755859375,
          "LARGE": 0.1907958984375,
          "OTHER": 0.5064697265625
        },
        "p0": {
          "mean_std": {
            "mean": 0.049643461284802015,
            "std": 0.030171847777887454
          },
          "quantiles": {
            "p50": 0.04178311675786972,
            "p90": 0.08457316178828479,
            "p99": 0.16792343001812704
          }
        },
        "entropy": {
          "mean_std": {
            "mean": 1.4734613366591036,
            "std": 0.17667414553603852
          },
          "quantiles": {
            "p50": 1.4960775599894791,
            "p90": 1.6900896384400954,
            "p99": 1.8049682735736834
          }
        },
        "s_eff": {
          "mean_std": {
            "mean": 4.553102337836345,
            "std": 0.6345255115888973
          },
          "quantiles": {
            "p50": 4.58083980401199,
            "p90": 5.34119405181383,
            "p99": 5.939068889108965
          }
        }
      },
      "xsum": {
        "count": 10486,
        "state_counts": {
          "NULL": 0,
          "UNIFORM": 1363,
          "SMALL": 1484,
          "LARGE": 2872,
          "OTHER": 4767
        },
        "state_ratio": {
          "NULL": 0.0,
          "UNIFORM": 0.1299828342551974,
          "SMALL": 0.14152202937249667,
          "LARGE": 0.27388899485027657,
          "OTHER": 0.4546061415220294
        },
        "p0": {
          "mean_std": {
            "mean": 0.06418167062313532,
            "std": 0.04765356682546106
          },
          "quantiles": {
            "p50": 0.0501585379242897,
            "p90": 0.11942879064008594,
            "p99": 0.25640989937819514
          }
        },
        "entropy": {
          "mean_std": {
            "mean": 1.4873130528587912,
            "std": 0.1773318471728427
          },
          "quantiles": {
            "p50": 1.5103191909700038,
            "p90": 1.7026533257737282,
            "p99": 1.8199454131573884
          }
        },
        "s_eff": {
          "mean_std": {
            "mean": 4.750551226813394,
            "std": 0.7126803417098657
          },
          "quantiles": {
            "p50": 4.79614042560852,
            "p90": 5.631939380785089,
            "p99": 6.418864512366683
          }
        }
      },
      "all": {
        "count": 26870,
        "state_counts": {
          "NULL": 0,
          "UNIFORM": 3292,
          "SMALL": 4515,
          "LARGE": 5998,
          "OTHER": 13065
        },
        "state_ratio": {
          "NULL": 0.0,
          "UNIFORM": 0.12251581689616672,
          "SMALL": 0.1680312616300707,
          "LARGE": 0.2232229251953852,
          "OTHER": 0.4862299962783774
        },
        "p0": {
          "mean_std": {
            "mean": 0.05531698801058404,
            "std": 0.038620943143403884
          },
          "quantiles": {
            "p50": 0.04444117471575737,
            "p90": 0.09778977613896132,
            "p99": 0.21069763645529765
          }
        },
        "entropy": {
          "mean_std": {
            "mean": 1.4788669598846313,
            "std": 0.1770600801375222
          },
          "quantiles": {
            "p50": 1.5007785575020858,
            "p90": 1.695103605367428,
            "p99": 1.810876462676003
          }
        },
        "s_eff": {
          "mean_std": {
            "mean": 4.630156638164344,
            "std": 0.6730446873208454
          },
          "quantiles": {
            "p50": 4.6553604499057535,
            "p90": 5.459600870173321,
            "p99": 6.174328532197354
          }
        }
      }
    },
    "L10_H2": {
      "hotpotqa": {
        "count": 16384,
        "state_counts": {
          "NULL": 0,
          "UNIFORM": 1929,
          "SMALL": 3031,
          "LARGE": 3126,
          "OTHER": 8298
        },
        "state_ratio": {
          "NULL": 0.0,
          "UNIFORM": 0.11773681640625,
          "SMALL": 0.18499755859375,
          "LARGE": 0.1907958984375,
          "OTHER": 0.5064697265625
        },
        "p0": {
          "mean_std": {
            "mean": 0.049643461284802015,
            "std": 0.030171847777887454
          },
          "quantiles": {
            "p50": 0.04178311675786972,
            "p90": 0.08457316178828479,
            "p99": 0.16792343001812704
          }
        },
        "entropy": {
          "mean_std": {
            "mean": 1.4734613366591036,
            "std": 0.17667414553603852
          },
          "quantiles": {
            "p50": 1.4960775599894791,
            "p90": 1.6900896384400954,
            "p99": 1.8049682735736834
          }
        },
        "s_eff": {
          "mean_std": {
            "mean": 4.553102337836345,
            "std": 0.6345255115888973
          },
          "quantiles": {
            "p50": 4.58083980401199,
            "p90": 5.34119405181383,
            "p99": 5.939068889108965
          }
        }
      },
      "xsum": {
        "count": 10486,
        "state_counts": {
          "NULL": 0,
          "UNIFORM": 1363,
          "SMALL": 1484,
          "LARGE": 2872,
          "OTHER": 4767
        },
        "state_ratio": {
          "NULL": 0.0,
          "UNIFORM": 0.1299828342551974,
          "SMALL": 0.14152202937249667,
          "LARGE": 0.27388899485027657,
          "OTHER": 0.4546061415220294
        },
        "p0": {
          "mean_std": {
            "mean": 0.06418167062313532,
            "std": 0.04765356682546106
          },
          "quantiles": {
            "p50": 0.0501585379242897,
            "p90": 0.11942879064008594,
            "p99": 0.25640989937819514
          }
        },
        "entropy": {
          "mean_std": {
            "mean": 1.4873130528587912,
            "std": 0.1773318471728427
          },
          "quantiles": {
            "p50": 1.5103191909700038,
            "p90": 1.7026533257737282,
            "p99": 1.8199454131573884
          }
        },
        "s_eff": {
          "mean_std": {
            "mean": 4.750551226813394,
            "std": 0.7126803417098657
          },
          "quantiles": {
            "p50": 4.79614042560852,
            "p90": 5.631939380785089,
            "p99": 6.418864512366683
          }
        }
      },
      "all": {
        "count": 26870,
        "state_counts": {
          "NULL": 0,
          "UNIFORM": 3292,
          "SMALL": 4515,
          "LARGE": 5998,
          "OTHER": 13065
        },
        "state_ratio": {
          "NULL": 0.0,
          "UNIFORM": 0.12251581689616672,
          "SMALL": 0.1680312616300707,
          "LARGE": 0.2232229251953852,
          "OTHER": 0.4862299962783774
        },
        "p0": {
          "mean_std": {
            "mean": 0.05531698801058404,
            "std": 0.038620943143403884
          },
          "quantiles": {
            "p50": 0.04444117471575737,
            "p90": 0.09778977613896132,
            "p99": 0.21069763645529765
          }
        },
        "entropy": {
          "mean_std": {
            "mean": 1.4788669598846313,
            "std": 0.1770600801375222
          },
          "quantiles": {
            "p50": 1.5007785575020858,
            "p90": 1.695103605367428,
            "p99": 1.810876462676003
          }
        },
        "s_eff": {
          "mean_std": {
            "mean": 4.630156638164344,
            "std": 0.6730446873208454
          },
          "quantiles": {
            "p50": 4.6553604499057535,
            "p90": 5.459600870173321,
            "p99": 6.174328532197354
          }
        }
      }
    }
  }
}